pybangla/__init__.py
pybangla/eval_pybangla.py
pybangla/eval_pybangla_3.0.x.py
pybangla/report_generation.py
pybangla/test.py
pybangla/year2year.py
pybangla/module/__init__.py
pybangla/module/config.py
pybangla/module/currency.py
pybangla/module/date_extractor.py
pybangla/module/driving_license.py
pybangla/module/email_url_normalization.py
pybangla/module/helpline_extractor.py
pybangla/module/main.py
pybangla/module/multiple_dot_number_processing.py
pybangla/module/nid_num_normalize.py
pybangla/module/number_parser.py
pybangla/module/number_pronunciation.py
pybangla/module/number_service.py
pybangla/module/ordinals_normalizaiton.py
pybangla/module/parser.py
pybangla/module/passport_num_normalize.py
pybangla/module/phone_number_extractor.py
pybangla/module/product_number.py
pybangla/module/product_unit_normalization.py
pybangla/module/security_code.py
pybangla/module/symbol_conversion.py
pybangla/module/word_to_number.py
pybangla/module/db/symbols_mapping.json
pybangla-3.0.4.dist-info/METADATA
pybangla-3.0.4.dist-info/WHEEL
pybangla-3.0.4.dist-info/top_level.txt
pybangla-3.0.4.dist-info/RECORD
