Metadata-Version: 2.4
Name: pybangla
Version: 3.0.4
Summary: pybangla is the bangla text normalizer tool, it use for text normalization like word to number and date formating purposes
Home-page: https://github.com/saiful9379/pybangla
Author: saiful
Author-email: saifulbrur79@gmail.com
License: MIT
Classifier: Programming Language :: Python :: 3
Classifier: License :: OSI Approved :: MIT License
Classifier: Operating System :: OS Independent
Requires-Python: >=3.6
Requires-Dist: DateTime
Requires-Dist: num2words
Requires-Dist: python-Levenshtein
Requires-Dist: fuzzywuzzy
Requires-Dist: loguru
Dynamic: author
Dynamic: author-email
Dynamic: classifier
Dynamic: description
Dynamic: description-content-type
Dynamic: home-page
Dynamic: license
Dynamic: requires-dist
Dynamic: requires-python
Dynamic: summary
